{
  "key":"GarbageRegistrationCertificate",
  "DataConfigs": {
    "version": "1.0.0",
    "baseKeyPath":"$.gb",
    "mappings":[
      {
        "direct":[
          {
            "variable":"applicationNumber",
            "value":{
              "path":"$.applicationNumber"
            }
          },
          {
           "variable":"qrCode",
            "value":{
              "path":"$.qrCodeText"
            },
            "type":"QRCODE"
          },
          {
           "variable":"ownerName",
            "value":{
              "path":"$.ownerName"
            }
          },
          {
           "variable":"propertyId",
            "value":{
              "path":"$.propertyId"
            }
          },
          {
           "variable":"address",
            "value":{
              "path":"$.address"
            }
          },
          {
           "variable":"createdTime",
            "value":{
              "path":"$.createdTime"
            }
          },
          {
           "variable":"mobileNumber",
            "value":{
              "path":"$.mobileNumber"
            }
          },
          {
           "variable":"userName",
            "value":{
              "path":"$.userName"
            }
          },
          {
           "variable":"approverName",
            "value":{
              "path":"$.approverName"
            }
          }
        ]
      }
    ]
  }
}